pyvider/__init__.py
pyvider/__main__.py
pyvider/handler.py
pyvider/capabilities/__init__.py
pyvider/capabilities/base.py
pyvider/capabilities/decorators.py
pyvider/cli/__init__.py
pyvider/cli/__main__.py
pyvider/cli/components_commands.py
pyvider/cli/config_commands.py
pyvider/cli/context.py
pyvider/cli/install_command.py
pyvider/cli/launch_context_command.py
pyvider/cli/main.py
pyvider/cli/provide_command.py
pyvider/cli/utils.py
pyvider/common/__init__.py
pyvider/common/config.py
pyvider/common/context.py
pyvider/common/encryption.py
pyvider/common/launch_context.py
pyvider/common/operation_context.py
pyvider/common/types.py
pyvider/common/utils/__init__.py
pyvider/common/utils/attrs_factory.py
pyvider/common/utils/availability.py
pyvider/conversion/__init__.py
pyvider/conversion/adapter.py
pyvider/conversion/marshaler.py
pyvider/conversion/schema_adapter.py
pyvider/conversion/utils.py
pyvider/conversion/context/__init__.py
pyvider/data_sources/__init__.py
pyvider/data_sources/base.py
pyvider/data_sources/decorators.py
pyvider/ephemerals/__init__.py
pyvider/ephemerals/base.py
pyvider/ephemerals/context.py
pyvider/ephemerals/decorators.py
pyvider/exceptions/__init__.py
pyvider/exceptions/base.py
pyvider/exceptions/foundation.py
pyvider/exceptions/function.py
pyvider/exceptions/grpc.py
pyvider/exceptions/provider.py
pyvider/exceptions/registry.py
pyvider/exceptions/resource.py
pyvider/exceptions/schema.py
pyvider/exceptions/serialization.py
pyvider/exceptions/validation.py
pyvider/functions/__init__.py
pyvider/functions/adapters.py
pyvider/functions/base.py
pyvider/functions/decorators.py
pyvider/hub/__init__.py
pyvider/hub/components.py
pyvider/hub/discovery.py
pyvider/hub/validators.py
pyvider/observability/__init__.py
pyvider/observability/metrics.py
pyvider/protocols/__init__.py
pyvider/protocols/service.py
pyvider/protocols/tfprotov6/__init__.py
pyvider/protocols/tfprotov6/utils.py
pyvider/protocols/tfprotov6/adapters/function_adapter.py
pyvider-0.0.1111.dist-info/licenses/LICENSE
pyvider-0.0.1111.dist-info/METADATA
pyvider-0.0.1111.dist-info/WHEEL
pyvider-0.0.1111.dist-info/entry_points.txt
pyvider-0.0.1111.dist-info/top_level.txt
pyvider-0.0.1111.dist-info/RECORD
