Metadata-Version: 2.4
Name: pyvider
Version: 0.0.1111
Summary: Python Terraform Provider Framework
Author-email: Tim Perkins <code@tim.life>
Maintainer-email: "provide.io" <code@provide.io>
License-Expression: Apache-2.0
Classifier: Development Status :: 3 - Alpha
Classifier: Intended Audience :: Developers
Classifier: Operating System :: OS Independent
Classifier: Programming Language :: Python :: 3
Classifier: Programming Language :: Python :: 3.11
Classifier: Programming Language :: Python :: 3.12
Classifier: Programming Language :: Python :: 3.13
Classifier: Typing :: Typed
Requires-Python: >=3.11
License-File: LICENSE
Requires-Dist: attrs>=25.1.0
Requires-Dist: click>=8.1.8
Requires-Dist: grpcio>=1.75.0
Requires-Dist: msgpack>=1.1.1
Requires-Dist: google>=3.0.0
Requires-Dist: cryptography>=42.0.8
Requires-Dist: tomli-w>=1.0.0
Requires-Dist: provide-foundation
Requires-Dist: pyvider-cty
Requires-Dist: pyvider-rpcplugin
Dynamic: license-file
